harpar/__init__.py
harpar-0.0.2.dist-info/WHEEL
harpar-0.0.2.dist-info/METADATA
harpar-0.0.2.dist-info/RECORD
