Metadata-Version: 2.1
Name: harpar
Version: 0.0.2
Summary: A Pythonic Har File Parser written Python3
Author: Dan Sikes
Author-email: dansikes7@gmail.com
Requires-Python: >=3.9,<4.0
Classifier: Programming Language :: Python :: 3
Classifier: Programming Language :: Python :: 3.10
Classifier: Programming Language :: Python :: 3.9
Requires-Dist: dacite (>=1.6.0,<2.0.0)
Requires-Dist: python-dateutil (>=2.8.2,<3.0.0)
